README.rst
setup.py
lishengangTools/__init__.py
lishengangTools/simpleEmail.py
lishengangTools.egg-info/PKG-INFO
lishengangTools.egg-info/SOURCES.txt
lishengangTools.egg-info/dependency_links.txt
lishengangTools.egg-info/top_level.txt