Metadata-Version: 1.0
Name: lishengangTools
Version: 0.0.5
Summary: personal python package of lishengang
Home-page: https://www.github.com
Author: lishengang
Author-email: cszy2013@163.com
License: BSD License
Platform: all
